rfpOperations/__init__.py
rfpOperations/database/__init__.py
rfpOperations/database/create.py
rfpOperations/database/delete.py
rfpOperations/database/funcs.py
rfpOperations/database/instance.py
rfpOperations/database/update.py
rfpOperations/identifier/__init__.py
rfpOperations/identifier/event.py
rfpOperations/identifier/hash_p_feature.py
rfpOperations/identifier/prop_identifier.py
rfpOperations/scraper/__init__.py
rfpOperations/scraper/base.py
rfpOperations/scraper/zoopla.py
rfpOperations-0.0.1.dist-info/METADATA
rfpOperations-0.0.1.dist-info/WHEEL
rfpOperations-0.0.1.dist-info/top_level.txt
rfpOperations-0.0.1.dist-info/RECORD
